spiders/__init__.py
spiders/barbara_spider.py
spiders/companynumberswithoutheaders.csv
spiders/officer_spider.py
spiders/psc_spider.py
cohospider-0.0.1.dist-info/METADATA
cohospider-0.0.1.dist-info/WHEEL
cohospider-0.0.1.dist-info/top_level.txt
cohospider-0.0.1.dist-info/RECORD
