Metadata-Version: 2.1
Name: cohospider
Version: 0.0.1
Summary: A package to scrape Companies House data
Project-URL: Homepage, https://github.com/Pometry/companies_house_scraper
Project-URL: Bug Tracker, https://github.com/Pometry/companies_house_scraper/issues
Requires-Python: >=3.7
Requires-Dist: Scrapy (>=2.8.0)
